num_fh/__init__.py
num_fh/about.py
num_fh/api/__init__.py
num_fh/api/downloader.py
num_fh/demo/__init__.py
num_fh/demo/server.py
num_fh/identification/__init__.py
num_fh/identification/data/__init__.py
num_fh/identification/data/find_fh.py
num_fh/identification/data/process_sentences.py
num_fh/identification/data/tree2numeric_fh.py
num_fh/identification/data/utils.py
num_fh/identification/features/__init__.py
num_fh/identification/features/build_features.py
num_fh/identification/models/__init__.py
num_fh/identification/models/linear_model.py
num_fh/resolution/__init__.py
num_fh/resolution/evaluate.py
num_fh/resolution/analysis/__init__.py
num_fh/resolution/analysis/agreement.py
num_fh/resolution/framework/__init__.py
num_fh/resolution/framework/evaluate.py
num_fh/resolution/framework/dataset_readers/__init__.py
num_fh/resolution/framework/dataset_readers/nfh_oracle_reader.py
num_fh/resolution/framework/dataset_readers/nfh_reader.py
num_fh/resolution/framework/models/__init__.py
num_fh/resolution/framework/models/model_base.py
num_fh/resolution/framework/predictors/__init__.py
num_fh/resolution/framework/predictors/model_base_predictor.py
tests/__init__.py
tests/test_nfh.py
num_fh-1.1.1.dist-info/LICENSE
num_fh-1.1.1.dist-info/METADATA
num_fh-1.1.1.dist-info/WHEEL
num_fh-1.1.1.dist-info/top_level.txt
num_fh-1.1.1.dist-info/RECORD
