Metadata-Version: 2.1
Name: num-fh
Version: 1.1.1
Summary: numeric fused-head identification and resolution
Home-page: http://nlp.biu.ac.il/~lazary/fh/
Author: Yanai Elazar and Yoav Goldberg
Author-email: yanaiela@gmail.com
License: MIT
Keywords: nlp numbers missing-elements spacy SpaCy
Platform: UNKNOWN
Requires-Dist: tensorboard-logger
Requires-Dist: docopt
Requires-Dist: gensim
Requires-Dist: numpy
Requires-Dist: sklearn
Requires-Dist: click
Requires-Dist: stanfordcorenlp (==3.8.0.1)
Requires-Dist: spacy
Requires-Dist: nltk
Requires-Dist: statsmodels
Requires-Dist: allennlp
Requires-Dist: Flask
